bossICC/BOSSExceptions.py
bossICC/BossICC.py
bossICC/CamForthTranslations.py
bossICC/DAQInterface.py
bossICC/FilenameGen.py
bossICC/__init__.py
bossICC/pixel_check.py
bossICC/Commands/BaseDelegate.py
bossICC/Commands/CamCmd.py
bossICC/Commands/Exposure.py
bossICC/Commands/ExposureCmd.py
bossICC/Commands/MechCmd.py
bossICC/Commands/PingCmd.py
bossICC/Commands/StatusCmd.py
bossICC/Commands/TopCmd.py
bossICC/Commands/__init__.py
bossICC/Controllers/BaseController.py
bossICC/Controllers/BaseFactory.py
bossICC/Controllers/BaseProtocol.py
bossICC/Controllers/CamController.py
bossICC/Controllers/CamProtocol.py
bossICC/Controllers/DAQController.py
bossICC/Controllers/MechController.py
bossICC/Controllers/MechProtocol.py
bossICC/Controllers/__init__.py
bossICC/Controllers/sp1cam.py
bossICC/Controllers/sp1daq.py
bossICC/Controllers/sp1mech.py
bossICC/Simulators/BOSSSim.py
bossICC/Simulators/CamForthSimulator.py
bossICC/Simulators/KillSims.sh
bossICC/Simulators/SpecMechSimulator.py
bossICC/Simulators/StartSims.sh
bossICC/Simulators/__init__.py
bossICC/etc/benchboss.yaml
bossICC/etc/boss.yaml
bossICC/etc/CamProcedures/flush_sp1
bossICC/etc/CamProcedures/flush_sp2
bossICC/etc/CamProcedures/full_sp1
bossICC/etc/CamProcedures/full_sp2
bossICC/etc/CamProcedures/iack_sp1
bossICC/etc/CamProcedures/iack_sp2
bossICC/etc/CamProcedures/pre-integrate_sp1
bossICC/etc/CamProcedures/pre-integrate_sp2
bossICC/etc/CamProcedures/red
bossICC/test/__init__.py
bossICC/test/command_coverage.py
sdss_bossicc-6.0.4.dist-info/METADATA
sdss_bossicc-6.0.4.dist-info/WHEEL
sdss_bossicc-6.0.4.dist-info/entry_points.txt
sdss_bossicc-6.0.4.dist-info/licenses/LICENSE.md
sdss_bossicc-6.0.4.dist-info/RECORD
