Metadata-Version: 2.4
Name: sdss-bossICC
Version: 6.0.4
Summary: The BOSS Instrument Control Computer for APO.
Project-URL: Homepage, https://github.com/sdss/bossICC
Project-URL: Repository, https://github.com/sdss/bossICC
Author: Craig Loomis
Maintainer-email: José Sánchez-Gallego <gallegoj@uw.edu>
License: BSD-3-Clause
License-File: LICENSE.md
Requires-Python: <4,>=3.9
Requires-Dist: astropy>=4.3.1
Requires-Dist: click>=8.0.1
Requires-Dist: numpy>=1.21.1
Requires-Dist: sdss-actorcore>=5.0.4
Requires-Dist: sdsstools>=0.4.13
Requires-Dist: twisted>=21.7.0
